stitcher/__init__.py
stitcher/file_reader.py
stitcher/main.py
stitcher/reconstruction.py
stitcher/reconstructionNumba.py
stitcher/test/__init__.py
stitcher/test/unit.py
brain_stitcher-1.3.2.dist-info/LICENSE.txt
brain_stitcher-1.3.2.dist-info/METADATA
brain_stitcher-1.3.2.dist-info/WHEEL
brain_stitcher-1.3.2.dist-info/top_level.txt
brain_stitcher-1.3.2.dist-info/RECORD
