Metadata-Version: 2.1
Name: brain-stitcher
Version: 1.3.2
Summary: Stitcher - mesh builder
Author: Heitor Gessner
Author-email: <lab.metabio@gmail.com>
Project-URL: Source, https://github.com/labmetabio/Stitcher
Keywords: mesh,Sticher
Classifier: Development Status :: 4 - Beta
Classifier: Programming Language :: Python :: 3
Classifier: Operating System :: MacOS
Classifier: Operating System :: Microsoft :: Windows
Classifier: Operating System :: Unix
Requires-Python: >=3.0, <4
License-File: LICENSE.txt
Requires-Dist: numpy
